tests/system/__init__.py
tests/unit/__init__.py
tests/unit/test_base.py
tests/unit/test_friends.py
tests/unit/test_upapi.py
tests/unit/test_user.py
upapi/__init__.py
upapi/base.py
upapi/endpoints.py
upapi/exceptions.py
upapi/meta.py
upapi/pubsub.py
upapi/scopes.py
upapi/user/__init__.py
upapi/user/friends.py
upapi-0.7.1.dist-info/DESCRIPTION.rst
upapi-0.7.1.dist-info/METADATA
upapi-0.7.1.dist-info/RECORD
upapi-0.7.1.dist-info/WHEEL
upapi-0.7.1.dist-info/metadata.json
upapi-0.7.1.dist-info/top_level.txt
